pyHomie/__init__.py
pyHomie/device.py
pyHomie/mqttClient.py
pyHomie/node.py
pyHomie/properties.py
pyHomie/pyHomie.py
pyHomie/watchdog.py
pyHomie-0.0.4.dist-info/METADATA
pyHomie-0.0.4.dist-info/WHEEL
pyHomie-0.0.4.dist-info/top_level.txt
pyHomie-0.0.4.dist-info/RECORD
