Metadata-Version: 2.1
Name: pyHomie
Version: 0.0.4
Summary: A Python library for Homie Convention
Home-page: https://github.com/ms412/pyHomie
Download-URL: https://github.com/user/reponame/archive/v_01.tar.gz
Author: Markus Schiesse
Author-email: M.Schiesser@gmail.com
License: MIT
Keywords: mqtt,paho-mqtt,homie
Classifier: Development Status :: 3 - Alpha
Classifier: Environment :: Other Environment
Classifier: Intended Audience :: Developers
Classifier: Intended Audience :: Information Technology
Classifier: License :: Freeware
Classifier: Operating System :: OS Independent
Classifier: Programming Language :: Python
Classifier: Programming Language :: Python :: 3
Classifier: Programming Language :: Python :: 3.12
Classifier: Topic :: Software Development :: Libraries :: Python Modules
Classifier: Topic :: Home Automation
